redshift_mcp_server/__init__.py
redshift_mcp_server/__main__.py
redshift_mcp_server/models.py
redshift_mcp_server/server.py
redshift_mcp_server/util.py
mseep_redshift_mcp_server-0.1.1.dist-info/METADATA
mseep_redshift_mcp_server-0.1.1.dist-info/WHEEL
mseep_redshift_mcp_server-0.1.1.dist-info/entry_points.txt
mseep_redshift_mcp_server-0.1.1.dist-info/RECORD
